kvm_db/__init__.py
kvm_db/kv_db.py
kvm_db/model_db.py
kvm_db/backends/base.py
kvm_db/backends/dynamodb.py
kvm_db/backends/sqlite.py
kvm_db-0.1.6.dist-info/METADATA
kvm_db-0.1.6.dist-info/WHEEL
kvm_db-0.1.6.dist-info/RECORD
