Metadata-Version: 2.3
Name: kvm-db
Version: 0.1.6
Summary: Key-Value&Model Database
Project-URL: homepage, https://github.com/Ja-sonYun/kvm-db
Project-URL: repository, https://github.com/Ja-sonYun/kvm-db
Author-email: Ja-sonYun <killa30867@gmail.com>
License-Expression: MIT
Keywords: database,key-value,model,pydantic
Requires-Python: >=3.9
Requires-Dist: pydantic>=2.7.0
Provides-Extra: dynamodb
Requires-Dist: boto3>=1.34.125; extra == 'dynamodb'
